README.rst
setup.py
alarm/__init__.py
alarm/main.py
alarm.egg-info/PKG-INFO
alarm.egg-info/SOURCES.txt
alarm.egg-info/dependency_links.txt
alarm.egg-info/top_level.txt
bin/alarm