Metadata-Version: 1.1
Name: alarm
Version: 2.2
Summary: CLI Alarm Clock
Home-page: https://github.com/dslackw/alarm
Author: dslackw
Author-email: d.zlatanidis@gmail.com
License: UNKNOWN
Keywords: alarm,clock,CLI,terminal
Platform: UNKNOWN
Classifier: Development Status :: 5 - Production/Stable
Classifier: Environment :: Console
Classifier: License :: OSI Approved :: GNU General Public License v3 or later (GPLv3+)
Classifier: Operating System :: POSIX :: Linux
Classifier: Operating System :: Unix
Classifier: Programming Language :: Python
Classifier: Programming Language :: Python :: 2.5
Classifier: Programming Language :: Python :: 2.6
Classifier: Programming Language :: Python :: 2.7
Classifier: Programming Language :: Python :: 3
Classifier: Programming Language :: Python :: 3.0
Classifier: Programming Language :: Python :: 3.1
Classifier: Programming Language :: Python :: 3.2
Classifier: Programming Language :: Python :: 3.3
Classifier: Programming Language :: Python :: 3.4
Classifier: Topic :: Multimedia
Classifier: Topic :: Multimedia :: Sound/Audio :: Players
Classifier: Topic :: Utilities
